{
  "generated_at": "2026-07-21T17:33:01.367063+00:00",
  "method": "discovery tasks only; no scraping, verification, prices, or costs are invented",
  "schema_version": 1,
  "search_required_count": 3,
  "source_queue": "data/opportunity_review_queue.json",
  "task_count": 3,
  "tasks": [
    {
      "accepted_comparable_fields": [
        "source",
        "url",
        "price_nok",
        "condition",
        "captured_at",
        "verified"
      ],
      "asking_price_nok": 110000.0,
      "candidate_sources": [
        {
          "authorized": false,
          "search_url": "https://www.finn.no/bap/forsale/search.html?q=2023+LMC+Tandero+500K+Ny+%2F+Ubrukt+-+4+sengeplasser+-+Fast+dobbeltseng+-+WC+%C3%85ndalsnes+32+bud+26m+59s",
          "source": "FINN Torget",
          "status": "REVIEW_REQUIRED"
        },
        {
          "authorized": true,
          "search_url": "https://www.auksjonen.no/auksjoner/?q=2023+LMC+Tandero+500K+Ny+%2F+Ubrukt+-+4+sengeplasser+-+Fast+dobbeltseng+-+WC+%C3%85ndalsnes+32+bud+26m+59s",
          "source": "Auksjonen.no",
          "status": "REVIEW_REQUIRED"
        },
        {
          "authorized": false,
          "search_url": "https://www.google.com/search?q=2023+LMC+Tandero+500K+Ny+%2F+Ubrukt+-+4+sengeplasser+-+Fast+dobbeltseng+-+WC+%C3%85ndalsnes+32+bud+26m+59s+pris+Norge",
          "source": "Google Norway",
          "status": "REVIEW_REQUIRED"
        }
      ],
      "market_search_query": "2023 LMC Tandero 500K Ny / Ubrukt - 4 sengeplasser - Fast dobbeltseng - WC Åndalsnes 32 bud 26m 59s",
      "opportunity_id": "unified-auksjonen-612519",
      "opportunity_url": "https://www.auksjonen.no/auksjon/campingvogn/2023_LMC_Tandero_500K__Ny__Ubrukt_-_4_sengeplasser_-_Fast_dobbeltseng_-_WC/612519",
      "required_verified_comparables": 3,
      "status": "SEARCH_REQUIRED",
      "title": "2023 LMC Tandero 500K Ny / Ubrukt - 4 sengeplasser - Fast dobbeltseng - WC Åndalsnes 32 bud 26m 59s",
      "verification_rule": "Accept only after a reviewer confirms material similarity, an accessible URL, and a directly observed NOK price."
    },
    {
      "accepted_comparable_fields": [
        "source",
        "url",
        "price_nok",
        "condition",
        "captured_at",
        "verified"
      ],
      "asking_price_nok": 31000.0,
      "candidate_sources": [
        {
          "authorized": false,
          "search_url": "https://www.finn.no/bap/forsale/search.html?q=Kebony+Radiata+terrassebord%2C+smooth+22x148mm+%2F+Ca.+700lm+totalt+H%C3%B8nefoss+31+bud+26m+59s",
          "source": "FINN Torget",
          "status": "REVIEW_REQUIRED"
        },
        {
          "authorized": true,
          "search_url": "https://www.auksjonen.no/auksjoner/?q=Kebony+Radiata+terrassebord%2C+smooth+22x148mm+%2F+Ca.+700lm+totalt+H%C3%B8nefoss+31+bud+26m+59s",
          "source": "Auksjonen.no",
          "status": "REVIEW_REQUIRED"
        },
        {
          "authorized": false,
          "search_url": "https://www.google.com/search?q=Kebony+Radiata+terrassebord%2C+smooth+22x148mm+%2F+Ca.+700lm+totalt+H%C3%B8nefoss+31+bud+26m+59s+pris+Norge",
          "source": "Google Norway",
          "status": "REVIEW_REQUIRED"
        }
      ],
      "market_search_query": "Kebony Radiata terrassebord, smooth 22x148mm / Ca. 700lm totalt Hønefoss 31 bud 26m 59s",
      "opportunity_id": "unified-auksjonen-610944",
      "opportunity_url": "https://www.auksjonen.no/auksjon/overskuddsvarer/Kebony_Radiata_terrassebord_smooth_22x148mm__Ca_700lm_totalt/610944",
      "required_verified_comparables": 3,
      "status": "SEARCH_REQUIRED",
      "title": "Kebony Radiata terrassebord, smooth 22x148mm / Ca. 700lm totalt Hønefoss 31 bud 26m 59s",
      "verification_rule": "Accept only after a reviewer confirms material similarity, an accessible URL, and a directly observed NOK price."
    },
    {
      "accepted_comparable_fields": [
        "source",
        "url",
        "price_nok",
        "condition",
        "captured_at",
        "verified"
      ],
      "asking_price_nok": 4700.0,
      "candidate_sources": [
        {
          "authorized": false,
          "search_url": "https://www.finn.no/bap/forsale/search.html?q=Original+litografi+av+Espolin+Johnson+%E2%80%93+innrammet+Sem+31+bud+4m+59s",
          "source": "FINN Torget",
          "status": "REVIEW_REQUIRED"
        },
        {
          "authorized": true,
          "search_url": "https://www.auksjonen.no/auksjoner/?q=Original+litografi+av+Espolin+Johnson+%E2%80%93+innrammet+Sem+31+bud+4m+59s",
          "source": "Auksjonen.no",
          "status": "REVIEW_REQUIRED"
        },
        {
          "authorized": false,
          "search_url": "https://www.google.com/search?q=Original+litografi+av+Espolin+Johnson+%E2%80%93+innrammet+Sem+31+bud+4m+59s+pris+Norge",
          "source": "Google Norway",
          "status": "REVIEW_REQUIRED"
        }
      ],
      "market_search_query": "Original litografi av Espolin Johnson – innrammet Sem 31 bud 4m 59s",
      "opportunity_id": "unified-auksjonen-611959",
      "opportunity_url": "https://www.auksjonen.no/auksjon/torget/Original_litografi_av_Espolin_Johnson__innrammet/611959",
      "required_verified_comparables": 3,
      "status": "SEARCH_REQUIRED",
      "title": "Original litografi av Espolin Johnson – innrammet Sem 31 bud 4m 59s",
      "verification_rule": "Accept only after a reviewer confirms material similarity, an accessible URL, and a directly observed NOK price."
    }
  ]
}
