{
  "evidence": {
    "unified-auksjonen-610944": {
      "auction_fee_nok": null,
      "dismantling_cost_nok": null,
      "market_comparables": [],
      "missing_evidence": [
        "three_verified_market_comparables",
        "auction_fee_nok",
        "vat_status",
        "vat_nok",
        "transport_cost_nok",
        "dismantling_cost_nok",
        "storage_cost_nok",
        "repair_cost_nok",
        "other_costs_nok"
      ],
      "opportunity_id": "unified-auksjonen-610944",
      "other_costs_nok": null,
      "repair_cost_nok": null,
      "storage_cost_nok": null,
      "title": "Kebony Radiata terrassebord, smooth 22x148mm / Ca. 700lm totalt Hønefoss 31 bud 26m 59s",
      "transport_cost_nok": null,
      "url": "https://www.auksjonen.no/auksjon/overskuddsvarer/Kebony_Radiata_terrassebord_smooth_22x148mm__Ca_700lm_totalt/610944",
      "vat_nok": null,
      "vat_status": null,
      "verified": false
    },
    "unified-auksjonen-611959": {
      "auction_fee_nok": null,
      "dismantling_cost_nok": null,
      "market_comparables": [],
      "missing_evidence": [
        "three_verified_market_comparables",
        "auction_fee_nok",
        "vat_status",
        "vat_nok",
        "transport_cost_nok",
        "dismantling_cost_nok",
        "storage_cost_nok",
        "repair_cost_nok",
        "other_costs_nok"
      ],
      "opportunity_id": "unified-auksjonen-611959",
      "other_costs_nok": null,
      "repair_cost_nok": null,
      "storage_cost_nok": null,
      "title": "Original litografi av Espolin Johnson – innrammet Sem 31 bud 4m 59s",
      "transport_cost_nok": null,
      "url": "https://www.auksjonen.no/auksjon/torget/Original_litografi_av_Espolin_Johnson__innrammet/611959",
      "vat_nok": null,
      "vat_status": null,
      "verified": false
    },
    "unified-auksjonen-612519": {
      "auction_fee_nok": null,
      "dismantling_cost_nok": null,
      "market_comparables": [],
      "missing_evidence": [
        "three_verified_market_comparables",
        "auction_fee_nok",
        "vat_status",
        "vat_nok",
        "transport_cost_nok",
        "dismantling_cost_nok",
        "storage_cost_nok",
        "repair_cost_nok",
        "other_costs_nok"
      ],
      "opportunity_id": "unified-auksjonen-612519",
      "other_costs_nok": null,
      "repair_cost_nok": null,
      "storage_cost_nok": null,
      "title": "2023 LMC Tandero 500K Ny / Ubrukt - 4 sengeplasser - Fast dobbeltseng - WC Åndalsnes 32 bud 26m 59s",
      "transport_cost_nok": null,
      "url": "https://www.auksjonen.no/auksjon/campingvogn/2023_LMC_Tandero_500K__Ny__Ubrukt_-_4_sengeplasser_-_Fast_dobbeltseng_-_WC/612519",
      "vat_nok": null,
      "vat_status": null,
      "verified": false
    }
  },
  "evidence_count": 3,
  "generated_at": "2026-07-21T17:33:01.421398+00:00",
  "method": "verified evidence only; unknown values remain null; no estimates are created",
  "schema_version": 1,
  "verified_count": 0
}
